topsisAnubhav/__init__.py
Topsis_Anubhav_102097015-1.0.0.dist-info/METADATA
Topsis_Anubhav_102097015-1.0.0.dist-info/WHEEL
Topsis_Anubhav_102097015-1.0.0.dist-info/top_level.txt
Topsis_Anubhav_102097015-1.0.0.dist-info/RECORD
