Metadata-Version: 2.1
Name: Topsis-Anubhav-102097015
Version: 1.0.0
Summary: Topsis
Home-page: https://github.com/
Author: Anubhav Goyal
Author-email: agoyal6_be19@thapar.edu
License: MIT
Platform: UNKNOWN
Classifier: License :: OSI Approved :: MIT License
Classifier: Programming Language :: Python :: 3.6
Classifier: Programming Language :: Python :: 3.7
Classifier: Programming Language :: Python :: 3.8
